dff.v
//DFF with synchronous set and reset


module dff(q,qbar, d, set, reset, clk);
input d, set, reset, clk;
output reg q; output qbar;

assign qbar = ~q;

always @ (posedge clk)
	begin
		if(reset == 0)	q <= 0;
		else if (set == 0) q <= 1;
		else q <= d;
	end
endmodule

dff_tb.v
`timescale 10ms / 1ms
`include "dff.v"

module dff_tb();

reg d, set, reset, clk = 1'b0;
wire q,qbar;

dff uut(q,qbar, d, set, reset, clk);

initial begin 

	$dumpfile("dff.vcd");
	$dumpvars(0, dff_tb);
		#3;
	d = 0; set = 1; reset = 1; #10;
	d = 1; set = 0; reset = 1; #10;
	d = 1; set = 1; reset = 0; #10;
	d = 0; set = 0; reset = 0; #10;
	
	
	end

always begin 
	clk = ~clk; #4;
	end

initial begin
	#100; $finish;
	end
	
endmodule

verilog 1/dff.vcd
$date
	Fri May 15 17:52:39 2020
$end
$version
	Icarus Verilog
$end
$timescale
	1ms
$end
$scope module dff_tb $end
$var wire 1 ! qbar $end
$var wire 1 " q $end
$var reg 1 # clk $end
$var reg 1 $ d $end
$var reg 1 % reset $end
$var reg 1 & set $end
$scope module uut $end
$var wire 1 # clk $end
$var wire 1 $ d $end
$var wire 1 ! qbar $end
$var wire 1 % reset $end
$var wire 1 & set $end
$var reg 1 " q $end
$upscope $end
$upscope $end
$enddefinitions $end
#0
$dumpvars
x&
x%
x$
1#
x"
x!
$end
#30
1%
1&
0$
#40
0#
#80
1!
0"
1#
#120
0#
#130
0&
1$
#160
0!
1"
1#
#200
0#
#230
0%
1&
#240
1!
0"
1#
#280
0#
#320
1#
#330
0&
0$
