counter.v
//Counter with Synchronous Reset

module counter(rst, clk, count);
input rst, clk;
output reg [3:0] count = 4'b0000;

always @ (posedge clk)
	begin
		if(rst)
			count = 0;
		else
			count = count + 1;
	end
endmodule

counter_tb.v
`timescale 10ms / 1ms
`include "counter.v"

module counter_tb();
reg rst=0, clk = 0;
wire [3:0] count;

counter uut(rst, clk, count);

initial begin
	$dumpfile("counter.vcd");
	$dumpvars(0, counter_tb);
	
	end
	
always begin
		rst = ~rst; #25;
		end
	
always begin
	clk = ~clk; #4;
	end

initial begin
	#100;
	$finish;
	end

endmodule

async_counter.vcd
$date
	Sat May 16 18:46:01 2020
$end
$version
	Icarus Verilog
$end
$timescale
	1ms
$end
$scope module counter_tb $end
$var wire 4 ! count [3:0] $end
$var reg 1 " clk $end
$var reg 1 # rst $end
$scope module uut $end
$var wire 1 " clk $end
$var wire 1 # rst $end
$var reg 4 $ count [3:0] $end
$upscope $end
$upscope $end
$enddefinitions $end
#0
$dumpvars
b0 $
1#
1"
b0 !
$end
#40
0"
#80
1"
#120
0"
#160
1"
#200
0"
#240
1"
#250
0#
#280
0"
#320
b1 !
b1 $
1"
#360
0"
#400
b10 !
b10 $
1"
#440
0"
#480
b11 !
b11 $
1"
#500
b0 !
b0 $
1#
#520
0"
#560
1"
#600
0"
#640
1"
#680
0"
#720
1"
#750
0#
#760
0"
#800
b1 !
b1 $
1"
#840
0"
#880
b10 !
b10 $
1"
#920
0"
#960
b11 !
b11 $
1"
#1000
b0 !
b0 $
0"
1#
