counter.v
//Counter with Synchronous Reset

module counter(rst, clk, count);
input rst, clk;
output reg [3:0] count = 4'b0000;

always @ (posedge clk)
	begin
		if(rst)
			count = 0;
		else
			count = count + 1;
	end
endmodule

counter_tb.v
`timescale 10ms / 1ms
`include "counter.v"

module counter_tb();
reg rst=0, clk = 0;
wire [3:0] count;

counter uut(rst, clk, count);

initial begin
	$dumpfile("counter.vcd");
	$dumpvars(0, counter_tb);
	
	end
	
always begin
		rst = ~rst; #25;
		end
	
always begin
	clk = ~clk; #4;
	end

initial begin
	#100;
	$finish;
	end

endmodule

counter.vcd
$date
	Sun May 10 00:23:09 2020
$end
$version
	Icarus Verilog
$end
$timescale
	1ms
$end
$scope module counter_tb $end
$var wire 4 ! count [3:0] $end
$var reg 1 " clk $end
$var reg 1 # rst $end
$scope module uut $end
$var wire 1 " clk $end
$var wire 1 # rst $end
$var reg 4 $ count [3:0] $end
$upscope $end
$upscope $end
$enddefinitions $end
#0
$dumpvars
bx $
0#
0"
bx !
$end
#1000
b0 !
b0 $
1#
1"
#2000
0#
0"
#3000
b1 !
b1 $
1"
#4000
0"
#5000
b10 !
b10 $
1"
#6000
0"
#7000
b11 !
b11 $
1"
#8000
0"
#9000
b100 !
b100 $
1"
#10000
0"
#11000
b0 !
b0 $
1#
1"
#12000
0#
0"
#13000
b1 !
b1 $
1"
#14000
0"
#15000
b10 !
b10 $
1"
