mux2.v
module mux2 (a,b,s,y);
input a,b,s;
output reg y;

always @ (*)
	if(s)
		y = b;
		
	else 
		y = a;
		
endmodule

mux2_tb.v
`timescale 10ms / 1ms
`include "mux2.v"

module mux2_tb();
reg a,b,s;
wire y;

mux2 uut(a,b,s,y);

initial begin
	$dumpfile("mux2.vcd");
	$dumpvars(0, mux2_tb);
	
	a=0; b=0; s=0; #5;
	a=0; b=0; s=1; #5;
	a=0; b=1; s=0; #5;
	a=0; b=1; s=1; #5;
	a=1; b=0; s=0; #5;
	a=1; b=0; s=1; #5;
	a=1; b=1; s=0; #5;
	a=1; b=1; s=1; #5;
	
	$finish;
	end
endmodule

mux2.vcd
$date
	Sat May 16 13:02:45 2020
$end
$version
	Icarus Verilog
$end
$timescale
	1ms
$end
$scope module mux2_tb $end
$var wire 1 ! y $end
$var reg 1 " a $end
$var reg 1 # b $end
$var reg 1 $ s $end
$scope module uut $end
$var wire 1 " a $end
$var wire 1 # b $end
$var wire 1 $ s $end
$var reg 1 ! y $end
$upscope $end
$upscope $end
$enddefinitions $end
#0
$dumpvars
0$
0#
0"
0!
$end
#50
1$
#100
0$
1#
#150
1!
1$
#200
0$
0#
1"
#250
0!
1$
#300
1!
0$
1#
#350
1$
