shiftreg.v
module shiftreg(clk, clr, a,e);

input clk, clr, a;
output reg e;

reg b,c,d;

always @ (posedge clk)
	begin
		
		if(!clr)
			begin
					b<=0;
					c<=0;
					d<=0;
					e<=0;
					
			end
		
		else 
			begin
				b <= a;
				c <= b;
				d <= c;
				e <= d;
			end
		
	end
	
endmodule

shiftreg_tb.v
`timescale 10ms / 1ms
`include "shiftreg.v"

module shiftreg_tb();

reg clk=0, clr=1, a=0;
wire e;

shiftreg uut(clk,clr, a, e);

initial begin
	$dumpfile("shiftreg.vcd");
	$dumpvars(0, shiftreg_tb);
	#10; a=0;
	#10; a=1;
	#10; a=0;
	#10; a=1;
	
	#100;	
	$finish;
	end
	
always 
	begin
		#9; clk = ~clk;
	end

	
endmodule

shiftreg.vcd
$date
	Sun May 24 14:07:24 2020
$end
$version
	Icarus Verilog
$end
$timescale
	1ms
$end
$scope module shiftreg_tb $end
$var wire 1 ! e $end
$var reg 1 " a $end
$var reg 1 # clk $end
$var reg 1 $ clr $end
$scope module uut $end
$var wire 1 " a $end
$var wire 1 # clk $end
$var wire 1 $ clr $end
$var reg 1 % b $end
$var reg 1 & c $end
$var reg 1 ' d $end
$var reg 1 ! e $end
$upscope $end
$upscope $end
$enddefinitions $end
#0
$dumpvars
x'
x&
x%
1$
0#
0"
x!
$end
#90
0%
1#
#180
0#
#200
1"
#270
0&
1%
1#
#300
0"
#360
0#
#400
1"
#450
0'
1&
1#
#540
0#
#630
0!
1'
1#
#720
0#
#810
1!
1#
